mcp_server_schedule_manager_new.py
mcp_server_schedule_manager_new-0.1.0.dist-info/METADATA
mcp_server_schedule_manager_new-0.1.0.dist-info/WHEEL
mcp_server_schedule_manager_new-0.1.0.dist-info/entry_points.txt
mcp_server_schedule_manager_new-0.1.0.dist-info/RECORD
