Metadata-Version: 2.4
Name: mcp-server-schedule-manager-new
Version: 0.1.0
Summary: A new simple MCP schedule manager service
Author-email: hechangtian <15993091621@163.com>
Requires-Python: >=3.10
Requires-Dist: annotated-types==0.7.0
Requires-Dist: anyio==4.9.0
Requires-Dist: build==1.2.2.post1
Requires-Dist: certifi==2025.4.26
Requires-Dist: charset-normalizer==3.4.2
Requires-Dist: click==8.2.0
Requires-Dist: exceptiongroup==1.3.0
Requires-Dist: h11==0.16.0
Requires-Dist: httpcore==1.0.9
Requires-Dist: httpx-sse==0.4.0
Requires-Dist: httpx==0.28.1
Requires-Dist: idna==3.10
Requires-Dist: mcp==1.8.0
Requires-Dist: packaging==25.0
Requires-Dist: pydantic-core==2.33.2
Requires-Dist: pydantic-settings==2.9.1
Requires-Dist: pydantic==2.11.4
Requires-Dist: pyproject-hooks==1.2.0
Requires-Dist: python-dotenv==1.1.0
Requires-Dist: python-multipart==0.0.20
Requires-Dist: requests==2.32.3
Requires-Dist: sniffio==1.3.1
Requires-Dist: sse-starlette==2.3.4
Requires-Dist: starlette==0.46.2
Requires-Dist: tomli==2.2.1
Requires-Dist: typing-extensions==4.13.2
Requires-Dist: typing-inspection==0.4.0
Requires-Dist: urllib3==2.4.0
Requires-Dist: uvicorn==0.34.2
